{"data":{"id":"a6ef9879-4b79-4a07-9075-0f33df6a9603","workspaceId":"dfbc9223-2846-48ff-bda1-c2afc1e6e6f9","projectId":"51c40776-5d8e-463b-8a27-d64911bc6906","title":"Add two weeks to Phase 2","description":null,"reason":"Client scope expansion","impactScope":"SCHEDULE","impactCost":null,"impactDays":14,"status":"SUBMITTED","createdByUserId":"8406d901-4bc5-453a-be8f-684afdb0b281","approvedByUserId":null,"approvedAt":null,"rejectedByUserId":null,"rejectedAt":null,"rejectionReason":null,"implementedByUserId":null,"implementedAt":null,"createdAt":"2026-02-15T21:05:54.645Z","updatedAt":"2026-02-15T21:05:54.872Z"},"meta":{"timestamp":"2026-02-15T21:05:54.885Z","requestId":"7fd5a9a4-3e95-40e1-b5a1-da34167c5307"}}
