{"data":{"zephixEnv":"staging","nodeEnv":"staging","dbHost":"postgres.railway.internal","dbIdentity":{"serverAddr":"fd12:c270:ca54:0:a000:32:4d:7c","serverPort":5432,"systemIdentifier":"7539754227597242404"},"migrationCount":128,"latestMigration":"CreateWave3ATables17980248000000","gitSha":"1ae4ce0eaa3ea15721c08a86ea23f780828e5762","startedAt":"2026-02-15T20:59:35.216Z","timestamp":"2026-02-15T21:05:53.195Z"},"meta":{"timestamp":"2026-02-15T21:05:53.195Z","requestId":"27022b02-77ff-415c-93ec-7cc879fecb5d"}}
